Metadata-Version: 2.1
Name: rustdeskauto
Version: 1.0.0
Summary: rustdesk远程桌面自动化
Home-page: https://github.com/Mr-J-J/shouhou
Author: mrj
Author-email: 806189218@qq.com
Maintainer: jzk
Maintainer-email: 806189218@qq.com
License: BSD License
Platform: all
Classifier: Development Status :: 4 - Beta
Classifier: Operating System :: OS Independent
Classifier: Intended Audience :: Developers
Classifier: License :: OSI Approved :: BSD License
Classifier: Programming Language :: Python
Classifier: Programming Language :: Python :: Implementation
Classifier: Programming Language :: Python :: 2
Classifier: Programming Language :: Python :: 2.7
Classifier: Programming Language :: Python :: 3
Classifier: Programming Language :: Python :: 3.4
Classifier: Programming Language :: Python :: 3.5
Classifier: Programming Language :: Python :: 3.6
Classifier: Topic :: Software Development :: Libraries
